chanjo_ccds.py
setup.cfg
setup.py
chanjo_ccds.egg-info/PKG-INFO
chanjo_ccds.egg-info/SOURCES.txt
chanjo_ccds.egg-info/dependency_links.txt
chanjo_ccds.egg-info/not-zip-safe
chanjo_ccds.egg-info/requires.txt
chanjo_ccds.egg-info/top_level.txt