Metadata-Version: 1.1
Name: chanjo-ccds
Version: 0.4
Summary: CCDS to Chanjo BED converter
Home-page: https://github.com/robinandeer/chanjo-ccds
Author: Robin Andeer
Author-email: robin.andeer@gmail.com
License: MIT
Download-URL: https://github.com/robinandeer/chanjo-ccds
Keywords: coverage sequencing clinical exome completeness diagnostics
Platform: UNKNOWN
Classifier: Development Status :: 4 - Beta
Classifier: Intended Audience :: Science/Research
Classifier: License :: OSI Approved :: MIT License
Classifier: Natural Language :: English
Classifier: Programming Language :: Python :: 3.3
Classifier: Programming Language :: Python :: 2.7
Classifier: Topic :: Scientific/Engineering :: Bio-Informatics
